httptap/__init__.py
httptap/_pkgmeta.py
httptap/analyzer.py
httptap/cli.py
httptap/constants.py
httptap/exporter.py
httptap/formatters.py
httptap/http_client.py
httptap/implementations/__init__.py
httptap/implementations/dns.py
httptap/implementations/timing.py
httptap/implementations/tls.py
httptap/interfaces.py
httptap/models.py
httptap/render.py
httptap/request_executor.py
httptap/tls_inspector.py
httptap/utils.py
httptap/visualizer.py
httptap-0.4.3.dist-info/WHEEL
httptap-0.4.3.dist-info/entry_points.txt
httptap-0.4.3.dist-info/METADATA
httptap-0.4.3.dist-info/RECORD
