Metadata-Version: 2.3
Name: httptap
Version: 0.4.3
Summary: HTTP request visualizer with detailed timing breakdown (DNS → TCP → TLS → HTTP)
Keywords: http,https,performance,timing,dns,tls,ssl,networking,monitoring,diagnostics,waterfall,curl,httpx
Author: Sergei Ozeranskii
License: Apache-2.0
Classifier: Development Status :: 4 - Beta
Classifier: Intended Audience :: Developers
Classifier: Intended Audience :: System Administrators
Classifier: Topic :: Internet :: WWW/HTTP
Classifier: Topic :: System :: Networking :: Monitoring
Classifier: Topic :: Software Development :: Testing
Classifier: Topic :: Utilities
Classifier: License :: OSI Approved :: Apache Software License
Classifier: Programming Language :: Python :: 3
Classifier: Programming Language :: Python :: 3.10
Classifier: Programming Language :: Python :: 3.11
Classifier: Programming Language :: Python :: 3.12
Classifier: Programming Language :: Python :: 3.13
Classifier: Programming Language :: Python :: 3.14
Classifier: Programming Language :: Python :: 3 :: Only
Classifier: Environment :: Console
Classifier: Operating System :: OS Independent
Classifier: Operating System :: POSIX
Classifier: Operating System :: MacOS
Classifier: Operating System :: Microsoft :: Windows
Classifier: Typing :: Typed
Requires-Dist: httpx[http2,socks]>=0.28.1
Requires-Dist: rich>=14.2.0
Requires-Dist: dnspython>=2.8.0
Requires-Dist: argcomplete>=3.6.3 ; extra == 'completion'
Maintainer: Sergei Ozeranskii
Requires-Python: >=3.10
Project-URL: Homepage, https://github.com/ozeranskii/httptap
Project-URL: Documentation, https://github.com/ozeranskii/httptap?tab=readme-ov-file
Project-URL: Repository, https://github.com/ozeranskii/httptap.git
Project-URL: Issues, https://github.com/ozeranskii/httptap/issues
Project-URL: Changelog, https://github.com/ozeranskii/httptap/blob/main/CHANGELOG.md
Provides-Extra: completion
